metricconverterteam10/__init__.py
metricconverterteam10/__main__.py
metricconverterteam10/age_converter.py
metricconverterteam10/distance_converter.py
metricconverterteam10/number_converter.py
metricconverterteam10/time_zone_converter.py
metricconverterteam10-1.1.0.dist-info/LICENSE
metricconverterteam10-1.1.0.dist-info/METADATA
metricconverterteam10-1.1.0.dist-info/WHEEL
metricconverterteam10-1.1.0.dist-info/entry_points.txt
metricconverterteam10-1.1.0.dist-info/top_level.txt
metricconverterteam10-1.1.0.dist-info/RECORD
