Metadata-Version: 2.1
Name: metricconverterteam10
Version: 1.1.0
Summary: An example of a package developed with pyenv, built with build using setuptools, uploaded to PyPI using twine, and distributed via pip.
Author-email: Jonason Wu <jw5911@nyu.edu>, Alejandro Olazabal <ajo351@nyu.edu>, Fatema Nassar <fan6236@nyu.edu>, Junyi Dong <jd4634@nyu.edu>
License: GNU GENERAL PUBLIC LICENSE
Keywords: python,package,build,tutorial
Classifier: Programming Language :: Python :: 3
Classifier: Intended Audience :: Education
Classifier: License :: OSI Approved :: GNU General Public License v3 (GPLv3)
Classifier: Operating System :: OS Independent
Requires-Python: >=3.7
License-File: LICENSE
Requires-Dist: pytz
Provides-Extra: dev
Requires-Dist: pytest ; extra == 'dev'
Requires-Dist: pipenv ; extra == 'dev'
